Metadata-Version: 2.1
Name: MacLearn
Version: 1.0.0
Summary: A simple module for using Machine Learning in your code.
Home-page: UNKNOWN
Author: Sajedur Rahman Fiad
Author-email: neural.gen.official@gmail.com
License: UNKNOWN
Platform: UNKNOWN
